{
  "buttons": [
    { "name": "Определитель номера" },
    { "name": "Мир без границ" },
    { "name": "10Гб" },
    { "name": "Роуминг по Европе" },
    { "name": "Интернет и ТВ" },
    { "name": "Определитель номера Определитель номера" },
    { "name": "Мир без границ Мир без границ Мир без границ" },
    { "name": "Мир без границ Мир без границ Мир без границ" },
    { "name": "Мир без границ Мир без границ Мир без границ" },
    { "name": "Определитель номера Определитель номера" }
  ],
  "tableInfo1": [
    {
      "number": "+7 (900) 123-45-67",
      "tarif": "Альтернативный 620",
      "balance": "0",
      "status": true,
      "fullAccess": true,
      "description": "Ксения"
    },
    {
      "number": "+7 (900) 123-45-67",
      "tarif": "Специальный",
      "balance": "-20652.51",
      "status": false,
      "fullAccess": true,
      "description": "Алексей"
    },
    {
      "number": "+7 (900) 123-45-67",
      "tarif": "Адаптивный 1 2020",
      "balance": "0",
      "status": true,
      "fullAccess": false,
      "description": "Фёдор"
    },
    {
      "number": "+7 (900) 123-45-67",
      "tarif": "Москва Стратегический (КОРП) (SS)",
      "balance": "0",
      "status": true,
      "fullAccess": false,
      "description": "Ксения"
    }
  ],
  "tableInfo2": [
    {
      "number": "+7 (900) 123-45-67",
      "tarif": "Адаптивный 1 2020",
      "balance": "0",
      "status": true,
      "fullAccess": false,
      "description": "Фёдор"
    },
    {
      "number": "+7 (900) 123-45-67",
      "tarif": "Альтернативный 620",
      "balance": "940",
      "status": true,
      "fullAccess": true,
      "description": "Ксения"
    }
  ],
  "servTableInfo": [
    {
      "name": "Отмена роуминга по России",
      "description": "Услуга меняет тарификацию вызовов в поездках по России.Звонки на номера региона нахождения тарифицируются как местные, а вызовы в регион подключения становятся междугородними.",
      "date": "31.05.2019, 00:00:00",
      "price": "250",
      "typePrice": "В месяц",
      "actions": true
    },
    {
      "name": "Подписка WINK +30GB на 30 дней",
      "description": "Подписка WINK +30GB на 30 дней",
      "date": "31.05.2019, 00:00:00",
      "price": "199",
      "typePrice": "В месяц",
      "actions": false
    },
    {
      "name": "Отмена роуминга по России",
      "description": "Услуга меняет тарификацию вызовов в поездках по России.Звонки на номера региона нахождения тарифицируются как местные, а вызовы в регион подключения становятся междугородними.",
      "date": "31.05.2019, 00:00:00",
      "price": "600",
      "typePrice": "В месяц",
      "actions": false
    },
    {
      "name": "Подписка WINK на 30 дней",
      "description": "Услуга меняет тарификацию вызовов в поездках по России.Звонки на номера региона нахождения тарифицируются как местные, а вызовы в регион подключения становятся междугородними.",
      "date": "31.05.2019, 00:00:00",
      "price": "399",
      "typePrice": "В месяц",
      "actions": true
    }
  ],
  "accordion": [
    { "accordionTitle": "Подписка WINK" },
    { "accordionTitle": "Мобильный интернет" },
    { "accordionTitle": "Базовые услуги" },
    { "accordionTitle": "Остальные услуги" },
    { "accordionTitle": "SMS/MMS" }
  ],
  "expensesOperations": [
    {
      "date": "29.07.2024",
      "sum": "-1",
      "operationType": "Услуга",
      "description": "Услуга «Международная связь + роуминг»"
    },
    {
      "date": "29.07.2024",
      "sum": "-1",
      "operationType": "Услуга",
      "description": "Услуга «Международная связь + роуминг»"
    },
    {
      "date": "29.07.2024",
      "sum": "-1",
      "operationType": "Услуга",
      "description": "Услуга «Международная связь + роуминг»"
    },
    {
      "date": "29.07.2024",
      "sum": "-1",
      "operationType": "Услуга",
      "description": "Услуга «Международная связь + роуминг»"
    },
    {
      "date": "29.07.2024",
      "sum": "-1",
      "operationType": "Услуга",
      "description": "Услуга «Международная связь + роуминг»"
    },
    {
      "date": "29.07.2024",
      "sum": "-1",
      "operationType": "Услуга",
      "description": "Услуга «Международная связь + роуминг»"
    }
  ],
  "month": ["Июль", "Август", "Сентябрь", "Октябрь", "Ноябрь", "Декабрь", "Январь", "Февраль", "Март", "Апрель", "Май", "Июнь"],
  "remainders": [{
    "typeRemainder": "Минуты", "fullValue": "4000", "remainderValue": "3423"
  },{
    "typeRemainder": "СМС", "fullValue": "500", "remainderValue": "341"
  },{
    "typeRemainder": "Гигабайты", "fullValue": "-1", "remainderValue": "-1"
  }]
}
